jwin.py
jwin-0.0.3.dist-info/METADATA
jwin-0.0.3.dist-info/WHEEL
jwin-0.0.3.dist-info/entry_points.txt
jwin-0.0.3.dist-info/top_level.txt
jwin-0.0.3.dist-info/RECORD
