Metadata-Version: 2.1
Name: jwin
Version: 0.0.3
Summary: A package for visualization of aggregate data of "J League"
Home-page: https://github.com/Doraemon-desu/J-league
Author: ryosuke yamamoto
Author-email: ryosukey1724@gmail.com
License: UNKNOWN
Project-URL: Bug Tracker, https://github.com/Doraemon-desu/J-league
Platform: UNKNOWN
Classifier: Programming Language :: Python :: 3
Classifier: License :: OSI Approved :: MIT License
Classifier: Operating System :: OS Independent
Requires-Python: >=3.7
